sovrin/__init__.py
sovrin/__metadata__.py
sovrin/domain_transactions_builder_genesis
sovrin/domain_transactions_live_genesis
sovrin/domain_transactions_local_genesis
sovrin/domain_transactions_sandbox_genesis
sovrin/metadata.json
sovrin/pool_transactions_builder_genesis
sovrin/pool_transactions_live_genesis
sovrin/pool_transactions_local_genesis
sovrin/pool_transactions_sandbox_genesis
sovrin/pool_transactions_training_genesis
sovrin-1.2.0.dist-info/LICENSE
sovrin-1.2.0.dist-info/METADATA
sovrin-1.2.0.dist-info/WHEEL
sovrin-1.2.0.dist-info/top_level.txt
sovrin-1.2.0.dist-info/RECORD
